CHANGELOG.txt
MANIFEST.in
README.rst
django-requirements.txt
requirements.txt
setup.py
stub-requirements.txt
infusionsoft/__init__.py
infusionsoft/client.py
infusionsoft/gen_stubs.py
infusionsoft/query.py
infusionsoft/stubs.py
infusionsoft/version.py
infusionsoft/contrib/__init__.py
infusionsoft/contrib/django/__init__.py
infusionsoft/contrib/django/apps.py
infusionsoft/contrib/django/initialize.py
infusionsoft/vendor/__init__.py
infusionsoft/vendor/werkzeug/__init__.py
infusionsoft/vendor/werkzeug/local.py
infusionsoft_client.egg-info/PKG-INFO
infusionsoft_client.egg-info/SOURCES.txt
infusionsoft_client.egg-info/dependency_links.txt
infusionsoft_client.egg-info/top_level.txt