Metadata-Version: 1.1
Name: infusionsoft-client
Version: 1.3.0
Summary: Sexy Infusionsoft XML-RPC API client
Home-page: UNKNOWN
Author: Zach "theY4Kman" Kanzler
Author-email: they4kman@gmail.com
License: UNKNOWN
Platform: UNKNOWN
Classifier: Development Status :: 4 - Beta
Classifier: Intended Audience :: Developers
Classifier: License :: OSI Approved :: Apache Software License
Classifier: Programming Language :: Python
Classifier: Programming Language :: Python :: 3
Classifier: Topic :: Internet :: WWW/HTTP :: Dynamic Content :: CGI Tools/Libraries
